scfw/__init__.py
scfw/__main__.py
scfw/audit.py
scfw/constants.py
scfw/ecosystem.py
scfw/firewall.py
scfw/logger.py
scfw/main.py
scfw/package.py
scfw/package_manager.py
scfw/report.py
scfw/verifier.py
scfw/cli/__init__.py
scfw/cli/parser.py
scfw/configure/__init__.py
scfw/configure/dd_agent.py
scfw/configure/env.py
scfw/configure/interactive.py
scfw/loggers/__init__.py
scfw/loggers/dd_agent_logger.py
scfw/loggers/dd_api_logger.py
scfw/loggers/dd_logger.py
scfw/loggers/file_logger.py
scfw/package_managers/__init__.py
scfw/package_managers/pip.py
scfw/package_managers/poetry.py
scfw/package_managers/npm/__init__.py
scfw/package_managers/npm/temp_project.py
scfw/verifiers/__init__.py
scfw/verifiers/dd_verifier/__init__.py
scfw/verifiers/dd_verifier/dataset.py
scfw/verifiers/list_verifier/__init__.py
scfw/verifiers/list_verifier/findings_map.py
scfw/verifiers/osv_verifier/__init__.py
scfw/verifiers/osv_verifier/osv_advisory.py
scfw-2.5.0.dist-info/licenses/LICENSE
scfw-2.5.0.dist-info/licenses/LICENSE-3rdparty.csv
scfw-2.5.0.dist-info/licenses/NOTICE
scfw-2.5.0.dist-info/METADATA
scfw-2.5.0.dist-info/WHEEL
scfw-2.5.0.dist-info/entry_points.txt
scfw-2.5.0.dist-info/top_level.txt
scfw-2.5.0.dist-info/RECORD
