Metadata-Version: 2.4
Name: scfw
Version: 2.5.0
Summary: A tool for preventing the installation of malicious open-source packages
Author-email: Ian Kretz <ian.kretz@datadoghq.com>
Maintainer-email: Ian Kretz <ian.kretz@datadoghq.com>
Requires-Python: >=3.10
License-File: LICENSE
License-File: LICENSE-3rdparty.csv
License-File: NOTICE
Requires-Dist: cvss
Requires-Dist: datadog-api-client
Requires-Dist: inquirer
Requires-Dist: packaging
Requires-Dist: python-dotenv
Requires-Dist: pyyaml
Requires-Dist: requests
Dynamic: license-file
